uberlimb/__init__.py
uberlimb/frame.py
uberlimb/input_space.py
uberlimb/model/__init__.py
uberlimb/model/model.py
uberlimb/model/models_impl.py
uberlimb/parameters.py
uberlimb/post_fx/__init__.py
uberlimb/post_fx/palette/__init__.py
uberlimb/post_fx/palette/brand_palette.py
uberlimb/post_fx/palette/misc_palettes.py
uberlimb/renderer.py
uberlimb/scratch.py
uberlimb/video/__init__.py
uberlimb/video/animation.py
uberlimb/video/impl.py
uberlimb/video/video_recorder.py
uberlimb-0.9.1.dist-info/WHEEL
uberlimb-0.9.1.dist-info/METADATA
uberlimb-0.9.1.dist-info/RECORD
